{
  "main": {
    "id": "4b071092662cbe52",
    "type": "split",
    "children": [
      {
        "id": "5433d2384d807578",
        "type": "tabs",
        "children": [
          {
            "id": "d703fe413354a6a7",
            "type": "leaf",
            "state": {
              "type": "markdown",
              "state": {
                "file": "World/World.h.md",
                "mode": "source",
                "source": false
              }
            }
          },
          {
            "id": "bc17a9efbea90876",
            "type": "leaf",
            "state": {
              "type": "markdown",
              "state": {
                "file": "World/World.md",
                "mode": "source",
                "source": false
              }
            }
          },
          {
            "id": "c0bd3c5212ea939e",
            "type": "leaf",
            "state": {
              "type": "markdown",
              "state": {
                "file": "World/World.md",
                "mode": "source",
                "source": false
              }
            }
          },
          {
            "id": "948c88fcc11a95f3",
            "type": "leaf",
            "state": {
              "type": "markdown",
              "state": {
                "file": "World/HandleCollisions.md",
                "mode": "source",
                "source": false
              }
            }
          },
          {
            "id": "4672c29b1971be5f",
            "type": "leaf",
            "state": {
              "type": "markdown",
              "state": {
                "file": "Object/Object.md",
                "mode": "source",
                "source": false
              }
            }
          },
          {
            "id": "c167f6b3380f6e5c",
            "type": "leaf",
            "state": {
              "type": "markdown",
              "state": {
                "file": "Object/GameObject.cpp.md",
                "mode": "source",
                "source": false
              }
            }
          },
          {
            "id": "b34a480bb8561e6b",
            "type": "leaf",
            "state": {
              "type": "markdown",
              "state": {
                "file": "Object/Object.md",
                "mode": "source",
                "source": false
              }
            }
          },
          {
            "id": "78d4d1767c50f3bf",
            "type": "leaf",
            "state": {
              "type": "markdown",
              "state": {
                "file": "Project.md",
                "mode": "source",
                "source": false
              }
            }
          },
          {
            "id": "73a63ca93fd39e1c",
            "type": "leaf",
            "state": {
              "type": "markdown",
              "state": {
                "file": "Collisions/Collision Detection.md",
                "mode": "source",
                "source": false
              }
            }
          },
          {
            "id": "fb549f639bb8a68a",
            "type": "leaf",
            "state": {
              "type": "markdown",
              "state": {
                "file": "Collisions/Collision.h.md",
                "mode": "source",
                "source": false
              }
            }
          },
          {
            "id": "fcebf928dedd7564",
            "type": "leaf",
            "state": {
              "type": "markdown",
              "state": {
                "file": "Object/Rotate.md",
                "mode": "source",
                "source": false
              }
            }
          },
          {
            "id": "c55155270f7f8757",
            "type": "leaf",
            "state": {
              "type": "markdown",
              "state": {
                "file": "World/World.md",
                "mode": "source",
                "source": false
              }
            }
          },
          {
            "id": "210c6ff8ad2665da",
            "type": "leaf",
            "state": {
              "type": "markdown",
              "state": {
                "file": "World/AddObject.md",
                "mode": "source",
                "source": false
              }
            }
          }
        ],
        "currentTab": 11
      }
    ],
    "direction": "vertical"
  },
  "left": {
    "id": "dcf2d1fdefea2d82",
    "type": "split",
    "children": [
      {
        "id": "9b98ddb07801fb85",
        "type": "tabs",
        "children": [
          {
            "id": "bdb844d2474c5f30",
            "type": "leaf",
            "state": {
              "type": "file-explorer",
              "state": {
                "sortOrder": "alphabetical"
              }
            }
          },
          {
            "id": "b27d1c9a686778ec",
            "type": "leaf",
            "state": {
              "type": "search",
              "state": {
                "query": "",
                "matchingCase": false,
                "explainSearch": false,
                "collapseAll": false,
                "extraContext": false,
                "sortOrder": "alphabetical"
              }
            }
          },
          {
            "id": "33cd5188d6bf7d55",
            "type": "leaf",
            "state": {
              "type": "bookmarks",
              "state": {}
            }
          }
        ]
      }
    ],
    "direction": "horizontal",
    "width": 200,
    "collapsed": true
  },
  "right": {
    "id": "528ed344fde9c9d2",
    "type": "split",
    "children": [
      {
        "id": "f50c03218a3a4632",
        "type": "tabs",
        "children": [
          {
            "id": "b3e103d88327543e",
            "type": "leaf",
            "state": {
              "type": "backlink",
              "state": {
                "file": "World/World.md",
                "collapseAll": false,
                "extraContext": false,
                "sortOrder": "alphabetical",
                "showSearch": false,
                "searchQuery": "",
                "backlinkCollapsed": false,
                "unlinkedCollapsed": true
              }
            }
          },
          {
            "id": "b44cd0601bac6ae9",
            "type": "leaf",
            "state": {
              "type": "outgoing-link",
              "state": {
                "file": "World/World.md",
                "linksCollapsed": false,
                "unlinkedCollapsed": true
              }
            }
          },
          {
            "id": "923b6d1f53a8b84d",
            "type": "leaf",
            "state": {
              "type": "tag",
              "state": {
                "sortOrder": "frequency",
                "useHierarchy": true
              }
            }
          },
          {
            "id": "aa2a533457961a7f",
            "type": "leaf",
            "state": {
              "type": "outline",
              "state": {
                "file": "World/World.md"
              }
            }
          }
        ]
      }
    ],
    "direction": "horizontal",
    "width": 300,
    "collapsed": true
  },
  "left-ribbon": {
    "hiddenItems": {
      "switcher:Open quick switcher": false,
      "graph:Open graph view": false,
      "canvas:Create new canvas": false,
      "daily-notes:Open today's daily note": false,
      "templates:Insert template": false,
      "command-palette:Open command palette": false
    }
  },
  "active": "c55155270f7f8757",
  "lastOpenFiles": [
    "Object/Object.md",
    "Object/Grow.md",
    "Object/SetPosition.md",
    "World/World.md",
    "Object/ObjectProperties.md",
    "Object/Rotate.md",
    "Object/void UpdateModelMatrix().md",
    "Object/Translate.md",
    "tocomplete2.png",
    "tocomplete.png",
    "World/ApplyGravity.md",
    "Collisions/Separating Axis Theorem.md",
    "Collisions/Collision.h.md",
    "Collisions/Collision Detection.md",
    "Collisions/bool AreObjsColliding(vector(vec3), vector(vec3)).md",
    "Object/GameObject.h.md",
    "Project.md",
    "Object/SetRotation.md",
    "Object/SetScale.md",
    "World/Update.md",
    "World/HandleCollisions.md",
    "World/AddObject.md",
    "World/World.cpp.md",
    "Object/GameObject.cpp.md",
    "World/World.h.md",
    "Object/ObjectProperties",
    "Object",
    "Collisions",
    "World",
    "Welcome.md"
  ]
}